pyvectors/__init__.py
pyvectors-0.2.8.dist-info/LICENSE.txt
pyvectors-0.2.8.dist-info/METADATA
pyvectors-0.2.8.dist-info/WHEEL
pyvectors-0.2.8.dist-info/top_level.txt
pyvectors-0.2.8.dist-info/RECORD
