Metadata-Version: 2.1
Name: pyvectors
Version: 0.2.8
Summary: provides 3D position Vectors as Python objects
Home-page: https://github.com/divyajeettt/pyvectors
Author: Divyajeet Singh
Author-email: knightt1821@gmail.com
Classifier: Programming Language :: Python :: 3
Classifier: License :: OSI Approved :: MIT License
Classifier: Operating System :: OS Independent
License-File: LICENSE.txt
Requires-Dist: matplotlib
